pibooth_telegram_upload.py
pibooth_telegram_upload-1.0.2.dist-info/METADATA
pibooth_telegram_upload-1.0.2.dist-info/WHEEL
pibooth_telegram_upload-1.0.2.dist-info/entry_points.txt
pibooth_telegram_upload-1.0.2.dist-info/top_level.txt
pibooth_telegram_upload-1.0.2.dist-info/RECORD
