Metadata-Version: 2.1
Name: pibooth-telegram-upload
Version: 1.0.2
Summary: pibooth plugin for uploading pictures to Telegram
Home-page: https://github.com/sabatesduran/pibooth-telegram-upload
Author: Dídac Sabatés
Author-email: sabatesduran@gmail.com
License: GPLv3
Download-URL: https://github.com/sabatesduran/pibooth-telegram-upload/archive/1.0.2.tar.gz
Keywords: Raspberry Pi,camera,photobooth,telegram,chat,bot,channel
Platform: unix
Platform: linux
Classifier: Development Status :: 5 - Production/Stable
Classifier: Environment :: Other Environment
Classifier: Intended Audience :: Developers
Classifier: Intended Audience :: End Users/Desktop
Classifier: License :: OSI Approved :: GNU General Public License v3 or later (GPLv3+)
Classifier: Operating System :: POSIX :: Linux
Classifier: Programming Language :: Python :: 3.6
Classifier: Programming Language :: Python :: 3.7
Classifier: Programming Language :: Python :: 3.8
Classifier: Programming Language :: Python :: 3.9
Classifier: Natural Language :: English
Classifier: Topic :: Multimedia :: Graphics :: Capture :: Digital Camera
Requires-Python: >=3.6
Requires-Dist: pibooth (>=2.0.0)
Requires-Dist: python-telegram-bot (==13.12)
